jaxopensimplexnoise/simplex_noise4d.py
jaxopensimplexnoise/types.py
jaxopensimplexnoise-0.1.0.dist-info/LICENSE
jaxopensimplexnoise-0.1.0.dist-info/METADATA
jaxopensimplexnoise-0.1.0.dist-info/WHEEL
jaxopensimplexnoise-0.1.0.dist-info/top_level.txt
jaxopensimplexnoise-0.1.0.dist-info/RECORD
