Metadata-Version: 2.2
Name: jaxopensimplexnoise
Version: 0.1.0
Summary: OpenSimplex noise implemented in JAX
Author-email: Jack Saunders <SaundersJE97@gmail.com>
License: The MIT License (MIT)
Project-URL: Homepage, https://github.com/SaundersJE97/JaxOpenSimplexNoise
Requires-Python: >=3.7
License-File: LICENSE
Requires-Dist: jax>=0.4.0
Requires-Dist: numpy
